{"name":"As user I want to search on various pages","id":"search-functionality-regression-test;as-user-i-want-to-search-on-various-pages","testSteps":[{"number":1,"description":"Example: {searchPage\u003dTSA Pre FAQ, searchItem\u003dTSA Pre, year\u003d, month\u003d, category\u003d}","duration":20004,"startTime":"2020-03-05T14:57:08.380-05:00[America/New_York]","exception":{"errorType":"org.openqa.selenium.ElementNotVisibleException","message":"Timed out after 2 seconds. Element not available\nBuild info: version: \u00273.141.59\u0027, revision: \u0027e82be7d358\u0027, time: \u00272018-11-14T08:17:03\u0027\nSystem info: host: \u0027AFSWWD0CQT7LE1\u0027, ip: \u002710.84.12.45\u0027, os.name: \u0027Windows 10\u0027, os.arch: \u0027amd64\u0027, os.version: \u002710.0\u0027, java.version: \u00271.8.0_241\u0027\nDriver info: driver.version: unknown\nBuild info: version: \u00273.141.59\u0027, revision: \u0027e82be7d358\u0027, time: \u00272018-11-14T08:17:03\u0027\nSystem info: host: \u0027AFSWWD0CQT7LE1\u0027, ip: \u002710.84.12.45\u0027, os.name: \u0027Windows 10\u0027, os.arch: \u0027amd64\u0027, os.version: \u002710.0\u0027, java.version: \u00271.8.0_241\u0027\nDriver info: driver.version: unknown","stackTrace":[{"declaringClass":"TSAGOV.pages.travel.TSAGOVTSAPrecheckPage","methodName":"navigateToFaq","fileName":"TSAGOVTSAPrecheckPage.java","lineNumber":46},{"declaringClass":"TSAGOV.steps.TSAGOVTravelSteps","methodName":"navigateToFaq","fileName":"TSAGOVTravelSteps.java","lineNumber":351},{"declaringClass":"TSAGOV.glue.TSAGOVSearchRegressionGlue","methodName":"user_access_What_Can_I_Bring_page","fileName":"TSAGOVSearchRegressionGlue.java","lineNumber":68},{"declaringClass":"✽","methodName":"user access TSA Pre FAQ page","fileName":"src/test/resources/TSAGOVFeatures/TSAGOVSearchRegression.feature","lineNumber":6}]},"result":"ERROR","precondition":false,"level":0,"children":[{"number":2,"description":"Given user wants to perform search operation","duration":504,"startTime":"2020-03-05T14:57:08.382-05:00[America/New_York]","result":"SUCCESS","precondition":false,"level":1},{"number":3,"description":"When user access TSA Pre FAQ page","duration":19488,"startTime":"2020-03-05T14:57:08.889-05:00[America/New_York]","exception":{"errorType":"org.openqa.selenium.ElementNotVisibleException","message":"Timed out after 2 seconds. Element not available\nBuild info: version: \u00273.141.59\u0027, revision: \u0027e82be7d358\u0027, time: \u00272018-11-14T08:17:03\u0027\nSystem info: host: \u0027AFSWWD0CQT7LE1\u0027, ip: \u002710.84.12.45\u0027, os.name: \u0027Windows 10\u0027, os.arch: \u0027amd64\u0027, os.version: \u002710.0\u0027, java.version: \u00271.8.0_241\u0027\nDriver info: driver.version: unknown\nBuild info: version: \u00273.141.59\u0027, revision: \u0027e82be7d358\u0027, time: \u00272018-11-14T08:17:03\u0027\nSystem info: host: \u0027AFSWWD0CQT7LE1\u0027, ip: \u002710.84.12.45\u0027, os.name: \u0027Windows 10\u0027, os.arch: \u0027amd64\u0027, os.version: \u002710.0\u0027, java.version: \u00271.8.0_241\u0027\nDriver info: driver.version: unknown","stackTrace":[{"declaringClass":"TSAGOV.pages.travel.TSAGOVTSAPrecheckPage","methodName":"navigateToFaq","fileName":"TSAGOVTSAPrecheckPage.java","lineNumber":46},{"declaringClass":"TSAGOV.steps.TSAGOVTravelSteps","methodName":"navigateToFaq","fileName":"TSAGOVTravelSteps.java","lineNumber":351},{"declaringClass":"TSAGOV.glue.TSAGOVSearchRegressionGlue","methodName":"user_access_What_Can_I_Bring_page","fileName":"TSAGOVSearchRegressionGlue.java","lineNumber":68},{"declaringClass":"✽","methodName":"user access TSA Pre FAQ page","fileName":"src/test/resources/TSAGOVFeatures/TSAGOVSearchRegression.feature","lineNumber":6}]},"result":"ERROR","precondition":false,"level":1,"children":[{"number":4,"description":"Navigate to TSAGOV","duration":11343,"startTime":"2020-03-05T14:57:08.917-05:00[America/New_York]","screenshots":[{"screenshot":"51557ba7d1999c8b1965e607d79c785fcb3e1d72a4b396a1154088fd81be4a24.png","timeStamp":1583438240260}],"result":"SUCCESS","precondition":false,"level":2},{"number":5,"description":"Navigate to TSA travel","duration":5552,"startTime":"2020-03-05T14:57:20.262-05:00[America/New_York]","screenshots":[{"screenshot":"51557ba7d1999c8b1965e607d79c785fcb3e1d72a4b396a1154088fd81be4a24.png","timeStamp":1583438240263},{"screenshot":"06cd6a6aa304f0719cfd8c665f167812af77ecc6520e505b2650a10d892804e3.png","timeStamp":1583438240869},{"screenshot":"c1f20adfb81c3f1cb81e045d92916465c907eaa8cf57c1af9ad856ab3ba33c55.png","timeStamp":1583438245812},{"screenshot":"c1f20adfb81c3f1cb81e045d92916465c907eaa8cf57c1af9ad856ab3ba33c55.png","timeStamp":1583438245814}],"result":"SUCCESS","precondition":false,"level":2},{"number":6,"description":"Navigate to faq","duration":2555,"startTime":"2020-03-05T14:57:25.815-05:00[America/New_York]","screenshots":[{"screenshot":"c1f20adfb81c3f1cb81e045d92916465c907eaa8cf57c1af9ad856ab3ba33c55.png","timeStamp":1583438245816},{"screenshot":"c1f20adfb81c3f1cb81e045d92916465c907eaa8cf57c1af9ad856ab3ba33c55.png","htmlSource":"pagesource4915726080974675972.html.txt","timeStamp":1583438248366}],"exception":{"errorType":"org.openqa.selenium.ElementNotVisibleException","message":"Timed out after 2 seconds. Element not available\nBuild info: version: \u00273.141.59\u0027, revision: \u0027e82be7d358\u0027, time: \u00272018-11-14T08:17:03\u0027\nSystem info: host: \u0027AFSWWD0CQT7LE1\u0027, ip: \u002710.84.12.45\u0027, os.name: \u0027Windows 10\u0027, os.arch: \u0027amd64\u0027, os.version: \u002710.0\u0027, java.version: \u00271.8.0_241\u0027\nDriver info: driver.version: unknown","stackTrace":[{"declaringClass":"TSAGOV.pages.travel.TSAGOVTSAPrecheckPage","methodName":"navigateToFaq","fileName":"TSAGOVTSAPrecheckPage.java","lineNumber":46},{"declaringClass":"TSAGOV.steps.TSAGOVTravelSteps","methodName":"navigateToFaq","fileName":"TSAGOVTravelSteps.java","lineNumber":351},{"declaringClass":"TSAGOV.glue.TSAGOVSearchRegressionGlue","methodName":"user_access_What_Can_I_Bring_page","fileName":"TSAGOVSearchRegressionGlue.java","lineNumber":68},{"declaringClass":"cucumber.runner.Runner","methodName":"runPickle","fileName":"Runner.java","lineNumber":80}]},"result":"ERROR","precondition":false,"level":2}]},{"number":7,"description":"And user searches on page TSA Pre FAQ for text TSA Pre, year , month , category ","duration":1,"startTime":"2020-03-05T14:57:28.378-05:00[America/New_York]","result":"SKIPPED","precondition":false,"level":1},{"number":8,"description":"Then search result is displayed on page TSA Pre FAQ for text TSA Pre, year , month ","duration":1,"startTime":"2020-03-05T14:57:28.380-05:00[America/New_York]","result":"SKIPPED","precondition":false,"level":1}]}],"userStory":{"id":"search-functionality-regression-test","storyName":"Search Functionality regression test","path":"src/test/resources/TSAGOVFeatures/TSAGOVSearchRegression.feature","type":"feature"},"featureTag":{"name":"TSAGOV features/Search Functionality regression test","type":"feature","displayName":"TSAGOV features/Search Functionality regression test"},"title":"As user I want to search on various pages","startTime":"2020-03-05T14:57:08.336-05:00[America/New_York]","duration":20048,"testFailureCause":{"errorType":"org.openqa.selenium.ElementNotVisibleException","message":"Timed out after 2 seconds. Element not available\nBuild info: version: \u00273.141.59\u0027, revision: \u0027e82be7d358\u0027, time: \u00272018-11-14T08:17:03\u0027\nSystem info: host: \u0027AFSWWD0CQT7LE1\u0027, ip: \u002710.84.12.45\u0027, os.name: \u0027Windows 10\u0027, os.arch: \u0027amd64\u0027, os.version: \u002710.0\u0027, java.version: \u00271.8.0_241\u0027\nDriver info: driver.version: unknown","stackTrace":[{"declaringClass":"TSAGOV.pages.travel.TSAGOVTSAPrecheckPage","methodName":"navigateToFaq","fileName":"TSAGOVTSAPrecheckPage.java","lineNumber":46},{"declaringClass":"TSAGOV.steps.TSAGOVTravelSteps","methodName":"navigateToFaq","fileName":"TSAGOVTravelSteps.java","lineNumber":351},{"declaringClass":"TSAGOV.glue.TSAGOVSearchRegressionGlue","methodName":"user_access_What_Can_I_Bring_page","fileName":"TSAGOVSearchRegressionGlue.java","lineNumber":68},{"declaringClass":"cucumber.runner.Runner","methodName":"runPickle","fileName":"Runner.java","lineNumber":80}]},"testFailureClassname":"org.openqa.selenium.ElementNotVisibleException","testFailureMessage":"Timed out after 2 seconds. Element not available\nBuild info: version: \u00273.141.59\u0027, revision: \u0027e82be7d358\u0027, time: \u00272018-11-14T08:17:03\u0027\nSystem info: host: \u0027AFSWWD0CQT7LE1\u0027, ip: \u002710.84.12.45\u0027, os.name: \u0027Windows 10\u0027, os.arch: \u0027amd64\u0027, os.version: \u002710.0\u0027, java.version: \u00271.8.0_241\u0027\nDriver info: driver.version: unknown","testFailureSummary":"ERROR;org.openqa.selenium.ElementNotVisibleException;Timed out after 2 seconds. Element not available\nBuild info: version: \u00273.141.59\u0027, revision: \u0027e82be7d358\u0027, time: \u00272018-11-14T08:17:03\u0027\nSystem info: host: \u0027AFSWWD0CQT7LE1\u0027, ip: \u002710.84.12.45\u0027, os.name: \u0027Windows 10\u0027, os.arch: \u0027amd64\u0027, os.version: \u002710.0\u0027, java.version: \u00271.8.0_241\u0027\nDriver info: driver.version: unknown;TSAGOVTSAPrecheckPage.java","projectKey":"","annotatedResult":"ERROR","sessionId":"e3961a17b42bc4e4bbc6c4e292e1693b","driver":"chrome","isManualTestingUpToDate":false,"dataTable":{"headers":["searchPage","searchItem","year","month","category"],"rows":[{"values":["TSA Pre FAQ","TSA Pre","","",""],"result":"ERROR"}],"predefinedRows":true,"scenarioOutline":"Given user wants to perform search operation\n\rWhen user access \u003csearchPage\u003e page\n\rAnd user searches on page \u003csearchPage\u003e for text \u003csearchItem\u003e, year \u003cyear\u003e, month \u003cmonth\u003e, category \u003ccategory\u003e\n\rThen search result is displayed on page \u003csearchPage\u003e for text \u003csearchItem\u003e, year \u003cyear\u003e, month \u003cmonth\u003e\n\r","dataSetDescriptors":[{"startRow":0,"rowCount":0,"name":""}]},"manual":false,"testSource":"Cucumber","result":"ERROR","scenarioOutline":"Given user wants to perform search operation\r\nWhen user access \u003csearchPage\u003e page\r\nAnd user searches on page \u003csearchPage\u003e for text \u003csearchItem\u003e, year \u003cyear\u003e, month \u003cmonth\u003e, category \u003ccategory\u003e\r\nThen search result is displayed on page \u003csearchPage\u003e for text \u003csearchItem\u003e, year \u003cyear\u003e, month \u003cmonth\u003e"}